ahk_binary/__init__.py
ahk_binary-2025.1.0.data/data/Scripts/AutoHotkey.exe
ahk_binary-2025.1.0.data/data/Scripts/AutoHotkeyV2.exe
ahk_binary-2025.1.0.dist-info/AutoHotkey_LICENSE
ahk_binary-2025.1.0.dist-info/LICENSE
ahk_binary-2025.1.0.dist-info/METADATA
ahk_binary-2025.1.0.dist-info/WHEEL
ahk_binary-2025.1.0.dist-info/top_level.txt
ahk_binary-2025.1.0.dist-info/RECORD
