Metadata-Version: 2.2
Name: ahk-binary
Version: 2025.1.0
Summary: Convenience for getting AutoHotkey.exe for the ahk package
Home-page: https://github.com/spyoungtech/ahk-binary
Author: Spencer Young
Author-email: spencer.young@spyoung.com
License: GNU General Public License v2 (GPLv2)
Classifier: License :: OSI Approved :: GNU General Public License v2 (GPLv2)
License-File: LICENSE
License-File: AutoHotkey_LICENSE
Dynamic: author
Dynamic: author-email
Dynamic: classifier
Dynamic: home-page
Dynamic: license
